Metadata-Version: 2.4
Name: adafruit-circuitpython-pcf8575
Version: 1.0.12
Summary: CircuitPython library for Adafruit PCF8575 GPIO expander
Author-email: Adafruit Industries <circuitpython@adafruit.com>
License: MIT
Project-URL: Homepage, https://github.com/adafruit/Adafruit_CircuitPython_PCF8575
Keywords: adafruit,blinka,circuitpython,micropython,pcf8575,pcf8575,i2c,gpio,expander,python,library
Classifier: Intended Audience :: Developers
Classifier: Topic :: Software Development :: Libraries
Classifier: Topic :: Software Development :: Embedded Systems
Classifier: Topic :: System :: Hardware
Classifier: License :: OSI Approved :: MIT License
Classifier: Programming Language :: Python :: 3
License-File: LICENSE
Requires-Dist: Adafruit-Blinka
Requires-Dist: adafruit-circuitpython-busdevice
Provides-Extra: optional
Dynamic: license-file
